painto/__init__.py
painto/color.py
painto/color_list.py
painto/list_base.py
painto/list_pride.py
painto/list_w3c.py
painto/list_xkcd.py
painto-0.3.0.dist-info/LICENSE
painto-0.3.0.dist-info/METADATA
painto-0.3.0.dist-info/WHEEL
painto-0.3.0.dist-info/RECORD
