Metadata-Version: 2.3
Name: painto
Version: 0.3.0
Summary: A flexible color library
License: MIT
Author: Michael Knowles
Requires-Python: >=3.12
Classifier: License :: OSI Approved :: MIT License
Classifier: Programming Language :: Python :: 3
Classifier: Programming Language :: Python :: 3.12
Classifier: Programming Language :: Python :: 3.13
Project-URL: Documentation, https://mapledyne.github.io/painto/
Project-URL: Source, https://github.com/mapledyne/painto/
